app/__init__.py
app/api.py
app/config.py
app/controllers/__init__.py
app/controllers/resources.py
app/controllers/upload.py
app/handlers/__init__.py
app/handlers/commons.py
app/handlers/errors.py
app/handlers/exceptions.py
app/handlers/messages.py
app/handlers/resources.py
app/handlers/singleton.py
app/handlers/validators.py
app/models/__init__.py
app/models/db_json_content.py
app/views/__init__.py
app/views/routes/resources.py
app/views/routes/upload.py
yet_another_json_server-1.0.3.dist-info/LICENSE
yet_another_json_server-1.0.3.dist-info/METADATA
yet_another_json_server-1.0.3.dist-info/WHEEL
yet_another_json_server-1.0.3.dist-info/entry_points.txt
yet_another_json_server-1.0.3.dist-info/RECORD
