Metadata-Version: 2.3
Name: yet-another-json-server
Version: 1.0.3
Summary: A REST API for JSON content with zero coding.
License: Apache-2.0
Author: Adriano Vieira
Author-email: adriano.svieira@gmail.com
Requires-Python: >=3.13,<4
Classifier: License :: OSI Approved :: Apache Software License
Classifier: Programming Language :: Python :: 3
Classifier: Programming Language :: Python :: 3.13
Requires-Dist: fastapi[standard] (>=0.116.1,<0.117.0)
Requires-Dist: pandas (>=2.3.1,<2.4.0)
Requires-Dist: python-dotenv (>=1.1.1,<1.2.0)
Requires-Dist: python-multipart (>=0.0.20,<0.1.0)
Requires-Dist: strawberry-graphql[debug-server] (>=0.278.1,<0.279.0)
Requires-Dist: unidecode (>=1.4.0,<1.5.0)
Project-URL: Bug Tracker, https://gitlab.com/adrianovieira/ya-json-server/-/issues
Project-URL: Documentation, https://gitlab.com/adrianovieira/ya-json-server
Project-URL: Repository, https://gitlab.com/adrianovieira/ya-json-server
